failureflags/__init__.py
failureflags-1.0.3.dist-info/licenses/LICENSE
failureflags-1.0.3.dist-info/METADATA
failureflags-1.0.3.dist-info/WHEEL
failureflags-1.0.3.dist-info/top_level.txt
failureflags-1.0.3.dist-info/RECORD
