Metadata-Version: 2.4
Name: failureflags
Version: 1.0.3
Summary: Failure Flags is a Python SDK for building application-level chaos experiments and reliability tests using the Gremlin Fault Injection platform.
Author-email: Jeff Nickoloff <jeff.nickoloff@gremlin.com>
Project-URL: Code, https://github.com/gremlin/failure-flags-python
Project-URL: Bug Tracker, https://github.com/gremlin/failure-flags-python/issues
Classifier: Programming Language :: Python :: 3
Classifier: License :: OSI Approved :: Apache Software License
Classifier: Operating System :: OS Independent
Requires-Python: >=3.7
License-File: LICENSE
Dynamic: license-file
